pybee/__init__.py
pybee/__version__.py
pybee/action/__init__.py
pybee/action/actions.py
pybee/action/ask.py
pybee/action/contexts.py
pybee/ask.py
pybee/awk.py
pybee/compress.py
pybee/datetime.py
pybee/download.py
pybee/git.py
pybee/github.py
pybee/importutil.py
pybee/netstat.py
pybee/network.py
pybee/path.py
pybee/pip.py
pybee/platform/__init__.py
pybee/platform/linux/__init__.py
pybee/platform/linux/firewalld.py
pybee/platform/linux/iptables.py
pybee/sed.py
pybee/shell.py
pybee/springboot.py
pybee/user.py
pybee-0.3.2.dist-info/WHEEL
pybee-0.3.2.dist-info/METADATA
pybee-0.3.2.dist-info/RECORD
