Metadata-Version: 2.1
Name: pybee
Version: 0.3.2
Summary: Provides some useful functions to write maintainer scripts or deployment scripts
License: BSD-4-Clause
Author: riag
Author-email: riag@163.com
Requires-Python: >=3.6,<4.0
Classifier: License :: OSI Approved :: BSD License
Classifier: License :: Other/Proprietary License
Classifier: Programming Language :: Python :: 3
Classifier: Programming Language :: Python :: 3.6
Classifier: Programming Language :: Python :: 3.7
Classifier: Topic :: Software Development :: Libraries :: Python Modules
Requires-Dist: PyFunctional (>=1.2,<2.0)
Requires-Dist: click (>=7.0,<8.0)
Requires-Dist: hfilesize (>=0.1.0,<0.2.0)
Requires-Dist: jinja2 (>=2.10,<3.0)
Requires-Dist: psutil (>=5.6,<6.0)
Requires-Dist: tqdm (>=4.31,<5.0)
